rgain/util.py
rgain/rgcalc.py
rgain/albumid.py
rgain/rgio.py
rgain/version.py
rgain/__init__.py
rgain/script/collectiongain.py
rgain/script/__init__.py
rgain/script/replaygain.py
rgain-1.3.2.dist-info/RECORD
rgain-1.3.2.dist-info/metadata.json
rgain-1.3.2.dist-info/DESCRIPTION.rst
rgain-1.3.2.dist-info/top_level.txt
rgain-1.3.2.dist-info/METADATA
rgain-1.3.2.dist-info/WHEEL
rgain-1.3.2.data/scripts/collectiongain
rgain-1.3.2.data/scripts/replaygain
