Metadata-Version: 2.0
Name: rgain
Version: 1.3.2
Summary: Multi-format Replay Gain utilities
Home-page: http://bitbucket.org/fk/rgain
Author: Felix Krull
Author-email: f_krull@gmx.de
License: GNU General Public License (v2 or later)
Platform: UNKNOWN
Classifier: Development Status :: 6 - Mature
Classifier: Environment :: Console
Classifier: Intended Audience :: End Users/Desktop
Classifier: Intended Audience :: Developers
Classifier: License :: OSI Approved :: GNU General Public License (GPL)
Classifier: Programming Language :: Python :: 2
Classifier: Topic :: Multimedia :: Sound/Audio :: Analysis
Classifier: Topic :: Software Development :: Libraries :: Python Modules
Requires: pygobject
Requires: mutagen
